{"nodes": [{"id": "home_kr_projects_trailarr_scripts_entrypoint_update_ytdlp_sh", "label": "update_ytdlp.sh", "file_type": "code", "source_file": "scripts/entrypoint/update_ytdlp.sh", "source_location": "L1", "metadata": {"language": "bash", "kind": "file"}}, {"id": "home_kr_projects_trailarr_scripts_entrypoint_update_ytdlp_sh__entry", "label": "update_ytdlp.sh script", "file_type": "code", "source_file": "scripts/entrypoint/update_ytdlp.sh", "source_location": "L1", "metadata": {"language": "bash", "kind": "bash_entrypoint"}}, {"id": "entrypoint_update_ytdlp_check_and_update_ytdlp", "label": "check_and_update_ytdlp()", "file_type": "code", "source_file": "scripts/entrypoint/update_ytdlp.sh", "source_location": "L17", "metadata": {"language": "bash", "kind": "bash_function"}}], "edges": [{"source": "home_kr_projects_trailarr_scripts_entrypoint_update_ytdlp_sh", "target": "home_kr_projects_trailarr_scripts_entrypoint_update_ytdlp_sh__entry", "relation": "contains", "confidence": "EXTRACTED", "source_file": "scripts/entrypoint/update_ytdlp.sh", "source_location": "L1", "weight": 1.0}, {"source": "home_kr_projects_trailarr_scripts_entrypoint_update_ytdlp_sh", "target": "entrypoint_update_ytdlp_check_and_update_ytdlp", "relation": "defines", "confidence": "EXTRACTED", "source_file": "scripts/entrypoint/update_ytdlp.sh", "source_location": "L17", "weight": 1.0}, {"source": "home_kr_projects_trailarr_scripts_entrypoint_update_ytdlp_sh", "target": "env_file", "relation": "imports", "confidence": "EXTRACTED", "source_file": "scripts/entrypoint/update_ytdlp.sh", "source_location": "L40", "weight": 1.0, "context": "import"}]}